{"statusCode": 200, "body": "{\n  \"success\": true,\n  \"opportunity_id\": \"006au000007dMheAAE\",\n  \"opportunity_name\": \"PwC Services Limited - Tivian - Renewal - 1497806 - 9_2025\",\n  \"account_id\": \"001au00000H3Bc3AAF\",\n  \"account_name\": \"PwC Services Limited\",\n  \"phone\": \"+4428 9024 5454\",\n  \"website\": \"http://www.pwcglobal.com\",\n  \"billing_address\": {\n    \"street\": \"Merchant Square \\r\\n20-22 Wellington Place\\r\\nVAT GB243823957 Customer company reg#: OC303525\",\n    \"city\": \"Belfast\",\n    \"state\": null,\n    \"postal_code\": \"BT1 6GE\",\n    \"country\": \"United Kingdom\"\n  },\n  \"billing_address_formatted\": \"Merchant Square \\r\\n20-22 Wellington Place\\r\\nVAT GB243823957 Customer company reg#: OC303525\\nBelfast, BT1 6GE\\nUnited Kingdom\",\n  \"shipping_address\": {\n    \"street\": \"Merchant Square \\r\\n20-22 Wellington Place\\r\\nVAT GB243823957 Customer company reg#: OC303525\",\n    \"city\": \"Belfast\",\n    \"state\": null,\n    \"postal_code\": \"BT1 6GE\",\n    \"country\": \"United Kingdom\"\n  },\n  \"shipping_address_formatted\": \"Merchant Square \\r\\n20-22 Wellington Place\\r\\nVAT GB243823957 Customer company reg#: OC303525\\nBelfast, BT1 6GE\\nUnited Kingdom\"\n}"}